{
  "id": "89a3a29d-892e-435a-b908-04d033d52f61",
  "prevId": "1111fbbf-a2e5-45b1-bcda-8da124ad3e7e",
  "version": "7",
  "dialect": "postgresql",
  "tables": {
    "public.cv_reviews": {
      "name": "cv_reviews",
      "schema": "",
      "columns": {
        "id": {
          "name": "id",
          "type": "uuid",
          "primaryKey": true,
          "notNull": true,
          "default": "gen_random_uuid()"
        },
        "user_id": {
          "name": "user_id",
          "type": "uuid",
          "primaryKey": false,
          "notNull": false
        },
        "target_role": {
          "name": "target_role",
          "type": "varchar(120)",
          "primaryKey": false,
          "notNull": true
        },
        "overall_score": {
          "name": "overall_score",
          "type": "integer",
          "primaryKey": false,
          "notNull": true
        },
        "result_json": {
          "name": "result_json",
          "type": "jsonb",
          "primaryKey": false,
          "notNull": true
        },
        "ai_provider": {
          "name": "ai_provider",
          "type": "varchar(50)",
          "primaryKey": false,
          "notNull": true
        },
        "ai_model": {
          "name": "ai_model",
          "type": "varchar(100)",
          "primaryKey": false,
          "notNull": true
        },
        "input_tokens": {
          "name": "input_tokens",
          "type": "integer",
          "primaryKey": false,
          "notNull": false
        },
        "output_tokens": {
          "name": "output_tokens",
          "type": "integer",
          "primaryKey": false,
          "notNull": false
        },
        "created_at": {
          "name": "created_at",
          "type": "timestamp",
          "primaryKey": false,
          "notNull": true,
          "default": "now()"
        }
      },
      "indexes": {},
      "foreignKeys": {},
      "compositePrimaryKeys": {},
      "uniqueConstraints": {},
      "policies": {},
      "checkConstraints": {},
      "isRLSEnabled": false
    },
    "public.review_attempts": {
      "name": "review_attempts",
      "schema": "",
      "columns": {
        "id": {
          "name": "id",
          "type": "uuid",
          "primaryKey": true,
          "notNull": true,
          "default": "gen_random_uuid()"
        },
        "identity_hash": {
          "name": "identity_hash",
          "type": "varchar(64)",
          "primaryKey": false,
          "notNull": true
        },
        "route": {
          "name": "route",
          "type": "varchar(120)",
          "primaryKey": false,
          "notNull": true
        },
        "created_at": {
          "name": "created_at",
          "type": "timestamp",
          "primaryKey": false,
          "notNull": true,
          "default": "now()"
        }
      },
      "indexes": {
        "review_attempts_identity_created_at_idx": {
          "name": "review_attempts_identity_created_at_idx",
          "columns": [
            {
              "expression": "identity_hash",
              "isExpression": false,
              "asc": true,
              "nulls": "last"
            },
            {
              "expression": "created_at",
              "isExpression": false,
              "asc": true,
              "nulls": "last"
            }
          ],
          "isUnique": false,
          "concurrently": false,
          "method": "btree",
          "with": {}
        }
      },
      "foreignKeys": {},
      "compositePrimaryKeys": {},
      "uniqueConstraints": {},
      "policies": {},
      "checkConstraints": {},
      "isRLSEnabled": false
    }
  },
  "enums": {},
  "schemas": {},
  "sequences": {},
  "roles": {},
  "policies": {},
  "views": {},
  "_meta": {
    "columns": {},
    "schemas": {},
    "tables": {}
  }
}